{
  "2022.10.27": [
    {
      "type": "IMAGE_CREATE",
      "name": "RPL-S_8+16",
      "githubRepo": "misdake/ChipAnnotationData7",
      "githubIssueId": 3,
      "insertTime": "Thu, 27 Oct 2022 13:45:57 GMT",
      "logType": "IMAGE_CREATE",
      "time": "Thu, 27 Oct 2022 13:45:57 GMT",
      "dateString": "2022.10.27"
    },
    {
      "type": "IMAGE_CREATE",
      "name": "Raptor_Cove_Core",
      "githubRepo": "misdake/ChipAnnotationData7",
      "githubIssueId": 4,
      "insertTime": "Thu, 27 Oct 2022 13:49:54 GMT",
      "logType": "IMAGE_CREATE",
      "time": "Thu, 27 Oct 2022 13:49:54 GMT",
      "dateString": "2022.10.27"
    },
    {
      "type": "IMAGE_CREATE",
      "name": "Gracemont_Cluster",
      "githubRepo": "misdake/ChipAnnotationData7",
      "githubIssueId": 5,
      "insertTime": "Thu, 27 Oct 2022 13:51:47 GMT",
      "logType": "IMAGE_CREATE",
      "time": "Thu, 27 Oct 2022 13:51:47 GMT",
      "dateString": "2022.10.27"
    },
    {
      "type": "IMAGE_CREATE",
      "name": "Gracemont_Core",
      "githubRepo": "misdake/ChipAnnotationData7",
      "githubIssueId": 6,
      "insertTime": "Thu, 27 Oct 2022 13:53:15 GMT",
      "logType": "IMAGE_CREATE",
      "time": "Thu, 27 Oct 2022 13:53:15 GMT",
      "dateString": "2022.10.27"
    }
  ],
  "2022.11.01": [
    {
      "type": "IMAGE_CREATE",
      "name": "CannonLake_2C_GT2",
      "githubRepo": "misdake/ChipAnnotationData7",
      "githubIssueId": 7,
      "insertTime": "Tue, 01 Nov 2022 13:20:26 GMT",
      "logType": "IMAGE_CREATE",
      "time": "Tue, 01 Nov 2022 13:20:26 GMT",
      "dateString": "2022.11.01"
    }
  ],
  "2023.06.04": [
    {
      "type": "IMAGE_CREATE",
      "name": "Raphael_IOD",
      "githubRepo": "misdake/ChipAnnotationData7",
      "githubIssueId": 8,
      "insertTime": "Sun, 04 Jun 2023 03:23:37 GMT",
      "logType": "IMAGE_CREATE",
      "time": "Sun, 04 Jun 2023 03:23:37 GMT",
      "dateString": "2023.06.04"
    },
    {
      "type": "IMAGE_CREATE",
      "name": "Zen4_CCD",
      "githubRepo": "misdake/ChipAnnotationData7",
      "githubIssueId": 9,
      "insertTime": "Sun, 04 Jun 2023 03:24:39 GMT",
      "logType": "IMAGE_CREATE",
      "time": "Sun, 04 Jun 2023 03:24:39 GMT",
      "dateString": "2023.06.04"
    },
    {
      "type": "IMAGE_CREATE",
      "name": "Zen4_Core",
      "githubRepo": "misdake/ChipAnnotationData7",
      "githubIssueId": 10,
      "insertTime": "Sun, 04 Jun 2023 03:26:14 GMT",
      "logType": "IMAGE_CREATE",
      "time": "Sun, 04 Jun 2023 03:26:14 GMT",
      "dateString": "2023.06.04"
    }
  ],
  "2023.06.17": [
    {
      "type": "IMAGE_CREATE",
      "name": "BayTrail",
      "githubRepo": "misdake/ChipAnnotationData7",
      "githubIssueId": 11,
      "insertTime": "Sat, 17 Jun 2023 05:37:51 GMT",
      "logType": "IMAGE_CREATE",
      "time": "Sat, 17 Jun 2023 05:37:51 GMT",
      "dateString": "2023.06.17"
    }
  ],
  "2023.07.29": [
    {
      "type": "IMAGE_CREATE",
      "name": "Bulldozer_Module",
      "githubRepo": "misdake/ChipAnnotationData3",
      "githubIssueId": 23,
      "insertTime": "Sat, 29 Jul 2023 06:54:15 GMT",
      "logType": "IMAGE_CREATE",
      "time": "Sat, 29 Jul 2023 06:54:15 GMT",
      "dateString": "2023.07.29"
    }
  ],
  "2023.09.03": [
    {
      "type": "IMAGE_CREATE",
      "name": "AD102",
      "githubRepo": "misdake/ChipAnnotationData2",
      "githubIssueId": 13,
      "insertTime": "Sun, 03 Sep 2023 13:47:50 GMT",
      "logType": "IMAGE_CREATE",
      "time": "Sun, 03 Sep 2023 13:47:50 GMT",
      "dateString": "2023.09.03"
    },
    {
      "type": "IMAGE_CREATE",
      "name": "Phoenix",
      "githubRepo": "misdake/ChipAnnotationData2",
      "githubIssueId": 14,
      "insertTime": "Sun, 03 Sep 2023 13:53:25 GMT",
      "logType": "IMAGE_CREATE",
      "time": "Sun, 03 Sep 2023 13:53:25 GMT",
      "dateString": "2023.09.03"
    }
  ],
  "2023.09.11": [
    {
      "type": "IMAGE_CREATE",
      "name": "Phoenix2",
      "githubRepo": "misdake/ChipAnnotationData2",
      "githubIssueId": 15,
      "insertTime": "Mon, 11 Sep 2023 09:16:37 GMT",
      "logType": "IMAGE_CREATE",
      "time": "Mon, 11 Sep 2023 09:16:37 GMT",
      "dateString": "2023.09.11"
    }
  ],
  "2023.11.06": [
    {
      "type": "IMAGE_CREATE",
      "name": "SandyBridge_EP",
      "githubRepo": "misdake/ChipAnnotationData8",
      "githubIssueId": 1,
      "insertTime": "Mon, 06 Nov 2023 12:25:34 GMT",
      "logType": "IMAGE_CREATE",
      "time": "Mon, 06 Nov 2023 12:25:34 GMT",
      "dateString": "2023.11.06"
    },
    {
      "type": "IMAGE_CREATE",
      "name": "IvyBridge_E",
      "githubRepo": "misdake/ChipAnnotationData8",
      "githubIssueId": 2,
      "insertTime": "Mon, 06 Nov 2023 12:26:53 GMT",
      "logType": "IMAGE_CREATE",
      "time": "Mon, 06 Nov 2023 12:26:53 GMT",
      "dateString": "2023.11.06"
    },
    {
      "type": "IMAGE_CREATE",
      "name": "Broadwell_2+2",
      "githubRepo": "misdake/ChipAnnotationData8",
      "githubIssueId": 3,
      "insertTime": "Mon, 06 Nov 2023 12:29:50 GMT",
      "logType": "IMAGE_CREATE",
      "time": "Mon, 06 Nov 2023 12:29:50 GMT",
      "dateString": "2023.11.06"
    },
    {
      "type": "IMAGE_CREATE",
      "name": "SW1621",
      "githubRepo": "misdake/ChipAnnotationData8",
      "githubIssueId": 4,
      "insertTime": "Mon, 06 Nov 2023 12:32:54 GMT",
      "logType": "IMAGE_CREATE",
      "time": "Mon, 06 Nov 2023 12:32:54 GMT",
      "dateString": "2023.11.06"
    },
    {
      "type": "IMAGE_CREATE",
      "name": "3C5000L",
      "githubRepo": "misdake/ChipAnnotationData8",
      "githubIssueId": 5,
      "insertTime": "Mon, 06 Nov 2023 12:37:18 GMT",
      "logType": "IMAGE_CREATE",
      "time": "Mon, 06 Nov 2023 12:37:18 GMT",
      "dateString": "2023.11.06"
    },
    {
      "type": "IMAGE_CREATE",
      "name": "Cezanne",
      "githubRepo": "misdake/ChipAnnotationData8",
      "githubIssueId": 6,
      "insertTime": "Mon, 06 Nov 2023 12:39:39 GMT",
      "logType": "IMAGE_CREATE",
      "time": "Mon, 06 Nov 2023 12:39:39 GMT",
      "dateString": "2023.11.06"
    },
    {
      "type": "IMAGE_CREATE",
      "name": "Exynos8890",
      "githubRepo": "misdake/ChipAnnotationData8",
      "githubIssueId": 7,
      "insertTime": "Mon, 06 Nov 2023 12:41:41 GMT",
      "logType": "IMAGE_CREATE",
      "time": "Mon, 06 Nov 2023 12:41:41 GMT",
      "dateString": "2023.11.06"
    },
    {
      "type": "IMAGE_CREATE",
      "name": "Snapdragon820",
      "githubRepo": "misdake/ChipAnnotationData8",
      "githubIssueId": 8,
      "insertTime": "Mon, 06 Nov 2023 12:45:10 GMT",
      "logType": "IMAGE_CREATE",
      "time": "Mon, 06 Nov 2023 12:45:10 GMT",
      "dateString": "2023.11.06"
    },
    {
      "type": "IMAGE_CREATE",
      "name": "Snapdragon888",
      "githubRepo": "misdake/ChipAnnotationData8",
      "githubIssueId": 9,
      "insertTime": "Mon, 06 Nov 2023 12:45:58 GMT",
      "logType": "IMAGE_CREATE",
      "time": "Mon, 06 Nov 2023 12:45:58 GMT",
      "dateString": "2023.11.06"
    }
  ],
  "2023.11.07": [
    {
      "type": "IMAGE_CREATE",
      "name": "A4",
      "githubRepo": "misdake/ChipAnnotationData8",
      "githubIssueId": 10,
      "insertTime": "Tue, 07 Nov 2023 15:05:07 GMT",
      "logType": "IMAGE_CREATE",
      "time": "Tue, 07 Nov 2023 15:05:07 GMT",
      "dateString": "2023.11.07"
    },
    {
      "type": "IMAGE_CREATE",
      "name": "A5X",
      "githubRepo": "misdake/ChipAnnotationData8",
      "githubIssueId": 12,
      "insertTime": "Tue, 07 Nov 2023 15:05:57 GMT",
      "logType": "IMAGE_CREATE",
      "time": "Tue, 07 Nov 2023 15:05:57 GMT",
      "dateString": "2023.11.07"
    },
    {
      "type": "IMAGE_CREATE",
      "name": "A6",
      "githubRepo": "misdake/ChipAnnotationData8",
      "githubIssueId": 13,
      "insertTime": "Tue, 07 Nov 2023 15:06:45 GMT",
      "logType": "IMAGE_CREATE",
      "time": "Tue, 07 Nov 2023 15:06:45 GMT",
      "dateString": "2023.11.07"
    },
    {
      "type": "IMAGE_CREATE",
      "name": "A7",
      "githubRepo": "misdake/ChipAnnotationData8",
      "githubIssueId": 14,
      "insertTime": "Tue, 07 Nov 2023 15:07:28 GMT",
      "logType": "IMAGE_CREATE",
      "time": "Tue, 07 Nov 2023 15:07:28 GMT",
      "dateString": "2023.11.07"
    },
    {
      "type": "IMAGE_CREATE",
      "name": "A9_TSMC",
      "githubRepo": "misdake/ChipAnnotationData8",
      "githubIssueId": 17,
      "insertTime": "Tue, 07 Nov 2023 15:10:42 GMT",
      "logType": "IMAGE_CREATE",
      "time": "Tue, 07 Nov 2023 15:10:42 GMT",
      "dateString": "2023.11.07"
    },
    {
      "type": "IMAGE_CREATE",
      "name": "A9X",
      "githubRepo": "misdake/ChipAnnotationData8",
      "githubIssueId": 18,
      "insertTime": "Tue, 07 Nov 2023 15:11:08 GMT",
      "logType": "IMAGE_CREATE",
      "time": "Tue, 07 Nov 2023 15:11:08 GMT",
      "dateString": "2023.11.07"
    },
    {
      "type": "IMAGE_CREATE",
      "name": "A10",
      "githubRepo": "misdake/ChipAnnotationData8",
      "githubIssueId": 19,
      "insertTime": "Tue, 07 Nov 2023 15:12:03 GMT",
      "logType": "IMAGE_CREATE",
      "time": "Tue, 07 Nov 2023 15:12:03 GMT",
      "dateString": "2023.11.07"
    },
    {
      "type": "IMAGE_CREATE",
      "name": "A11",
      "githubRepo": "misdake/ChipAnnotationData8",
      "githubIssueId": 20,
      "insertTime": "Tue, 07 Nov 2023 15:13:12 GMT",
      "logType": "IMAGE_CREATE",
      "time": "Tue, 07 Nov 2023 15:13:12 GMT",
      "dateString": "2023.11.07"
    },
    {
      "type": "IMAGE_CREATE",
      "name": "A12",
      "githubRepo": "misdake/ChipAnnotationData8",
      "githubIssueId": 21,
      "insertTime": "Tue, 07 Nov 2023 15:13:39 GMT",
      "logType": "IMAGE_CREATE",
      "time": "Tue, 07 Nov 2023 15:13:39 GMT",
      "dateString": "2023.11.07"
    },
    {
      "type": "IMAGE_CREATE",
      "name": "A14",
      "githubRepo": "misdake/ChipAnnotationData8",
      "githubIssueId": 23,
      "insertTime": "Tue, 07 Nov 2023 15:14:14 GMT",
      "logType": "IMAGE_CREATE",
      "time": "Tue, 07 Nov 2023 15:14:14 GMT",
      "dateString": "2023.11.07"
    },
    {
      "type": "IMAGE_CREATE",
      "name": "A15",
      "githubRepo": "misdake/ChipAnnotationData8",
      "githubIssueId": 24,
      "insertTime": "Tue, 07 Nov 2023 15:21:28 GMT",
      "logType": "IMAGE_CREATE",
      "time": "Tue, 07 Nov 2023 15:21:28 GMT",
      "dateString": "2023.11.07"
    },
    {
      "type": "IMAGE_CREATE",
      "name": "A5",
      "githubRepo": "misdake/ChipAnnotationData8",
      "githubIssueId": 11,
      "insertTime": "Tue, 07 Nov 2023 15:27:36 GMT",
      "logType": "IMAGE_CREATE",
      "time": "Tue, 07 Nov 2023 15:27:36 GMT",
      "dateString": "2023.11.07"
    }
  ],
  "2024.01.27": [
    {
      "type": "IMAGE_CREATE",
      "name": "OmniPath",
      "githubRepo": "misdake/ChipAnnotationData8",
      "githubIssueId": 25,
      "insertTime": "Sat, 27 Jan 2024 06:29:46 GMT",
      "logType": "IMAGE_CREATE",
      "time": "Sat, 27 Jan 2024 06:29:46 GMT",
      "dateString": "2024.01.27"
    },
    {
      "type": "IMAGE_CREATE",
      "name": "VanGogh",
      "githubRepo": "misdake/ChipAnnotationData8",
      "githubIssueId": 26,
      "insertTime": "Sat, 27 Jan 2024 06:32:07 GMT",
      "logType": "IMAGE_CREATE",
      "time": "Sat, 27 Jan 2024 06:32:07 GMT",
      "dateString": "2024.01.27"
    },
    {
      "type": "IMAGE_CREATE",
      "name": "MeteorLake_CPU_2+8",
      "githubRepo": "misdake/ChipAnnotationData8",
      "githubIssueId": 29,
      "insertTime": "Sat, 27 Jan 2024 12:43:49 GMT",
      "logType": "IMAGE_CREATE",
      "time": "Sat, 27 Jan 2024 12:43:49 GMT",
      "dateString": "2024.01.27"
    },
    {
      "type": "IMAGE_CREATE",
      "name": "MeteorLake_GPU",
      "githubRepo": "misdake/ChipAnnotationData8",
      "githubIssueId": 28,
      "insertTime": "Sat, 27 Jan 2024 12:44:36 GMT",
      "logType": "IMAGE_CREATE",
      "time": "Sat, 27 Jan 2024 12:44:36 GMT",
      "dateString": "2024.01.27"
    },
    {
      "type": "IMAGE_CREATE",
      "name": "MeteorLake_IO",
      "githubRepo": "misdake/ChipAnnotationData8",
      "githubIssueId": 30,
      "insertTime": "Sat, 27 Jan 2024 12:45:19 GMT",
      "logType": "IMAGE_CREATE",
      "time": "Sat, 27 Jan 2024 12:45:19 GMT",
      "dateString": "2024.01.27"
    },
    {
      "type": "IMAGE_CREATE",
      "name": "MeteorLake_SOC",
      "githubRepo": "misdake/ChipAnnotationData8",
      "githubIssueId": 27,
      "insertTime": "Sat, 27 Jan 2024 12:45:52 GMT",
      "logType": "IMAGE_CREATE",
      "time": "Sat, 27 Jan 2024 12:45:52 GMT",
      "dateString": "2024.01.27"
    },
    {
      "type": "IMAGE_CREATE",
      "name": "Navi23",
      "githubRepo": "misdake/ChipAnnotationData8",
      "githubIssueId": 31,
      "insertTime": "Sat, 27 Jan 2024 13:33:34 GMT",
      "logType": "IMAGE_CREATE",
      "time": "Sat, 27 Jan 2024 13:33:34 GMT",
      "dateString": "2024.01.27"
    }
  ],
  "2024.04.14": [
    {
      "type": "IMAGE_CREATE",
      "name": "Raphael_IOD_2",
      "githubRepo": "misdake/ChipAnnotationData8",
      "githubIssueId": 32,
      "insertTime": "Sun, 14 Apr 2024 14:53:46 GMT",
      "logType": "IMAGE_CREATE",
      "time": "Sun, 14 Apr 2024 14:53:46 GMT",
      "dateString": "2024.04.14"
    },
    {
      "type": "IMAGE_CREATE",
      "name": "AD102_2",
      "githubRepo": "misdake/ChipAnnotationData8",
      "githubIssueId": 33,
      "insertTime": "Sun, 14 Apr 2024 14:57:30 GMT",
      "logType": "IMAGE_CREATE",
      "time": "Sun, 14 Apr 2024 14:57:30 GMT",
      "dateString": "2024.04.14"
    }
  ],
  "2024.05.26": [
    {
      "type": "IMAGE_CREATE",
      "name": "GA106",
      "githubRepo": "misdake/ChipAnnotationData4",
      "githubIssueId": 5,
      "insertTime": "Sun, 26 May 2024 14:05:28 GMT",
      "logType": "IMAGE_CREATE",
      "time": "Sun, 26 May 2024 14:05:28 GMT",
      "dateString": "2024.05.26"
    },
    {
      "type": "IMAGE_CREATE",
      "name": "IvyBridgeEX",
      "githubRepo": "misdake/ChipAnnotationData4",
      "githubIssueId": 6,
      "insertTime": "Sun, 26 May 2024 14:11:34 GMT",
      "logType": "IMAGE_CREATE",
      "time": "Sun, 26 May 2024 14:11:34 GMT",
      "dateString": "2024.05.26"
    },
    {
      "type": "COMMENT_INSERT",
      "imageName": "GF108",
      "title": "ROPs+MC",
      "username": "misdake",
      "githubRepo": "misdake/ChipAnnotationData2",
      "githubIssueId": 10,
      "commentId": 2132253089,
      "insertTime": "Sun, 26 May 2024 15:05:53 GMT",
      "updateTime": "Sun, 26 May 2024 15:05:53 GMT",
      "logType": "COMMENT_INSERT",
      "time": "Sun, 26 May 2024 15:05:53 GMT",
      "dateString": "2024.05.26"
    }
  ],
  "2024.07.12": [
    {
      "type": "IMAGE_CREATE",
      "name": "Navi12",
      "githubRepo": "misdake/ChipAnnotationData8",
      "githubIssueId": 34,
      "insertTime": "Fri, 12 Jul 2024 15:01:17 GMT",
      "logType": "IMAGE_CREATE",
      "time": "Fri, 12 Jul 2024 15:01:17 GMT",
      "dateString": "2024.07.12"
    },
    {
      "type": "IMAGE_CREATE",
      "name": "Broadwell_4+4e",
      "githubRepo": "misdake/ChipAnnotationData8",
      "githubIssueId": 35,
      "insertTime": "Fri, 12 Jul 2024 15:06:56 GMT",
      "logType": "IMAGE_CREATE",
      "time": "Fri, 12 Jul 2024 15:06:56 GMT",
      "dateString": "2024.07.12"
    },
    {
      "type": "IMAGE_CREATE",
      "name": "Skylake_4+4e",
      "githubRepo": "misdake/ChipAnnotationData8",
      "githubIssueId": 36,
      "insertTime": "Fri, 12 Jul 2024 15:09:01 GMT",
      "logType": "IMAGE_CREATE",
      "time": "Fri, 12 Jul 2024 15:09:01 GMT",
      "dateString": "2024.07.12"
    },
    {
      "type": "IMAGE_CREATE",
      "name": "Arise1020",
      "githubRepo": "misdake/ChipAnnotationData8",
      "githubIssueId": 37,
      "insertTime": "Fri, 12 Jul 2024 15:11:46 GMT",
      "logType": "IMAGE_CREATE",
      "time": "Fri, 12 Jul 2024 15:11:46 GMT",
      "dateString": "2024.07.12"
    }
  ],
  "2024.07.28": [
    {
      "type": "COMMENT_INSERT",
      "imageName": "Zen2_CCD",
      "title": "Core Arch",
      "username": "misdake",
      "githubRepo": "misdake/ChipAnnotationData2",
      "githubIssueId": 2,
      "commentId": 2254352175,
      "insertTime": "Sun, 28 Jul 2024 05:44:54 GMT",
      "updateTime": "Tue, 30 Jul 2024 04:57:42 GMT",
      "logType": "COMMENT_INSERT",
      "time": "Sun, 28 Jul 2024 05:44:54 GMT",
      "dateString": "2024.07.28"
    },
    {
      "type": "COMMENT_INSERT",
      "imageName": "Zen3_CCD",
      "title": "Core Arch",
      "username": "misdake",
      "githubRepo": "misdake/ChipAnnotationData5",
      "githubIssueId": 1,
      "commentId": 2254352230,
      "insertTime": "Sun, 28 Jul 2024 05:45:14 GMT",
      "updateTime": "Fri, 02 Aug 2024 16:08:51 GMT",
      "logType": "COMMENT_INSERT",
      "time": "Sun, 28 Jul 2024 05:45:14 GMT",
      "dateString": "2024.07.28"
    },
    {
      "type": "COMMENT_INSERT",
      "imageName": "Zen4_Core",
      "title": "Core Arch",
      "username": "misdake",
      "githubRepo": "misdake/ChipAnnotationData7",
      "githubIssueId": 10,
      "commentId": 2254362633,
      "insertTime": "Sun, 28 Jul 2024 06:33:09 GMT",
      "updateTime": "Sun, 04 Aug 2024 14:15:22 GMT",
      "logType": "COMMENT_INSERT",
      "time": "Sun, 28 Jul 2024 06:33:09 GMT",
      "dateString": "2024.07.28"
    },
    {
      "type": "IMAGE_CREATE",
      "name": "StrixPoint",
      "githubRepo": "misdake/ChipAnnotationData8",
      "githubIssueId": 38,
      "insertTime": "Sun, 28 Jul 2024 13:51:55 GMT",
      "logType": "IMAGE_CREATE",
      "time": "Sun, 28 Jul 2024 13:51:55 GMT",
      "dateString": "2024.07.28"
    }
  ],
  "2024.07.30": [
    {
      "type": "COMMENT_UPDATE",
      "imageName": "Zen2_CCD",
      "title": "Core Arch",
      "username": "misdake",
      "githubRepo": "misdake/ChipAnnotationData2",
      "githubIssueId": 2,
      "commentId": 2254352175,
      "insertTime": "Sun, 28 Jul 2024 05:44:54 GMT",
      "updateTime": "Tue, 30 Jul 2024 04:57:42 GMT",
      "logType": "COMMENT_UPDATE",
      "time": "Tue, 30 Jul 2024 04:57:42 GMT",
      "dateString": "2024.07.30"
    },
    {
      "type": "COMMENT_INSERT",
      "imageName": "Zeppelin",
      "title": "Core Arch",
      "username": "misdake",
      "githubRepo": "misdake/ChipAnnotationData2",
      "githubIssueId": 5,
      "commentId": 2257503792,
      "insertTime": "Tue, 30 Jul 2024 05:36:58 GMT",
      "updateTime": "Tue, 30 Jul 2024 05:36:58 GMT",
      "logType": "COMMENT_INSERT",
      "time": "Tue, 30 Jul 2024 05:36:58 GMT",
      "dateString": "2024.07.30"
    }
  ],
  "2024.08.02": [
    {
      "type": "COMMENT_UPDATE",
      "imageName": "Zen3_CCD",
      "title": "Core Arch",
      "username": "misdake",
      "githubRepo": "misdake/ChipAnnotationData5",
      "githubIssueId": 1,
      "commentId": 2254352230,
      "insertTime": "Sun, 28 Jul 2024 05:45:14 GMT",
      "updateTime": "Fri, 02 Aug 2024 16:08:51 GMT",
      "logType": "COMMENT_UPDATE",
      "time": "Fri, 02 Aug 2024 16:08:51 GMT",
      "dateString": "2024.08.02"
    }
  ],
  "2024.08.04": [
    {
      "type": "COMMENT_UPDATE",
      "imageName": "Zen4_Core",
      "title": "Core Arch",
      "username": "misdake",
      "githubRepo": "misdake/ChipAnnotationData7",
      "githubIssueId": 10,
      "commentId": 2254362633,
      "insertTime": "Sun, 28 Jul 2024 06:33:09 GMT",
      "updateTime": "Sun, 04 Aug 2024 14:15:22 GMT",
      "logType": "COMMENT_UPDATE",
      "time": "Sun, 04 Aug 2024 14:15:22 GMT",
      "dateString": "2024.08.04"
    }
  ],
  "2024.08.15": [
    {
      "type": "IMAGE_CREATE",
      "name": "Zen5_CCD",
      "githubRepo": "misdake/ChipAnnotationData8",
      "githubIssueId": 39,
      "insertTime": "Thu, 15 Aug 2024 14:13:43 GMT",
      "logType": "IMAGE_CREATE",
      "time": "Thu, 15 Aug 2024 14:13:43 GMT",
      "dateString": "2024.08.15"
    },
    {
      "type": "IMAGE_CREATE",
      "name": "SapphireRapids",
      "githubRepo": "misdake/ChipAnnotationData8",
      "githubIssueId": 40,
      "insertTime": "Thu, 15 Aug 2024 14:16:23 GMT",
      "logType": "IMAGE_CREATE",
      "time": "Thu, 15 Aug 2024 14:16:23 GMT",
      "dateString": "2024.08.15"
    },
    {
      "type": "IMAGE_CREATE",
      "name": "MeteorLake_BaseDie",
      "githubRepo": "misdake/ChipAnnotationData8",
      "githubIssueId": 41,
      "insertTime": "Thu, 15 Aug 2024 14:21:14 GMT",
      "logType": "IMAGE_CREATE",
      "time": "Thu, 15 Aug 2024 14:21:14 GMT",
      "dateString": "2024.08.15"
    }
  ],
  "2024.09.14": [
    {
      "type": "IMAGE_CREATE",
      "name": "GV100",
      "githubRepo": "misdake/ChipAnnotationData8",
      "githubIssueId": 42,
      "insertTime": "Sat, 14 Sep 2024 14:43:19 GMT",
      "logType": "IMAGE_CREATE",
      "time": "Sat, 14 Sep 2024 14:43:19 GMT",
      "dateString": "2024.09.14"
    },
    {
      "type": "IMAGE_CREATE",
      "name": "MagnyCours_6C",
      "githubRepo": "misdake/ChipAnnotationData8",
      "githubIssueId": 43,
      "insertTime": "Sat, 14 Sep 2024 14:44:34 GMT",
      "logType": "IMAGE_CREATE",
      "time": "Sat, 14 Sep 2024 14:44:34 GMT",
      "dateString": "2024.09.14"
    },
    {
      "type": "IMAGE_CREATE",
      "name": "Interlagos_4M",
      "githubRepo": "misdake/ChipAnnotationData8",
      "githubIssueId": 44,
      "insertTime": "Sat, 14 Sep 2024 14:45:55 GMT",
      "logType": "IMAGE_CREATE",
      "time": "Sat, 14 Sep 2024 14:45:55 GMT",
      "dateString": "2024.09.14"
    },
    {
      "type": "COMMENT_INSERT",
      "imageName": "GV100",
      "title": "GPC Blocks",
      "username": "misdake",
      "githubRepo": "misdake/ChipAnnotationData8",
      "githubIssueId": 42,
      "commentId": 2351048950,
      "insertTime": "Sat, 14 Sep 2024 16:18:04 GMT",
      "updateTime": "Sat, 14 Sep 2024 16:25:26 GMT",
      "logType": "COMMENT_INSERT",
      "time": "Sat, 14 Sep 2024 16:18:04 GMT",
      "dateString": "2024.09.14"
    }
  ],
  "2024.09.16": [
    {
      "type": "IMAGE_CREATE",
      "name": "Tukwila",
      "githubRepo": "misdake/ChipAnnotationData8",
      "githubIssueId": 45,
      "insertTime": "Mon, 16 Sep 2024 14:42:44 GMT",
      "logType": "IMAGE_CREATE",
      "time": "Mon, 16 Sep 2024 14:42:44 GMT",
      "dateString": "2024.09.16"
    },
    {
      "type": "IMAGE_CREATE",
      "name": "Haswell_4+3e",
      "githubRepo": "misdake/ChipAnnotationData8",
      "githubIssueId": 46,
      "insertTime": "Mon, 16 Sep 2024 14:45:31 GMT",
      "logType": "IMAGE_CREATE",
      "time": "Mon, 16 Sep 2024 14:45:31 GMT",
      "dateString": "2024.09.16"
    },
    {
      "type": "IMAGE_CREATE",
      "name": "M2",
      "githubRepo": "misdake/ChipAnnotationData8",
      "githubIssueId": 47,
      "insertTime": "Mon, 16 Sep 2024 14:51:44 GMT",
      "logType": "IMAGE_CREATE",
      "time": "Mon, 16 Sep 2024 14:51:44 GMT",
      "dateString": "2024.09.16"
    }
  ]
}